froxpy.py
froxpy-1.0.1.dist-info/LICENSE
froxpy-1.0.1.dist-info/METADATA
froxpy-1.0.1.dist-info/WHEEL
froxpy-1.0.1.dist-info/top_level.txt
froxpy-1.0.1.dist-info/RECORD
