Metadata-Version: 2.1
Name: froxpy
Version: 1.0.1
Summary: A library to manage and test proxy lists in python
Home-page: https://github.com/lizardstudios-at/froxpy
Author: Lizard Studios
Author-email: support@lizard-studios.at
License: UNKNOWN
Platform: UNKNOWN
Requires-Dist: colorama
Requires-Dist: requests
